agentfud_password_manager/__init__.py
agentfud_password_manager/cli.py
agentfud_password_manager/models.py
agentfud_password_manager/utils.py
agentfud_password_manager/commands/cmd_add.py
agentfud_password_manager/commands/cmd_delete.py
agentfud_password_manager/commands/cmd_generate.py
agentfud_password_manager/commands/cmd_get.py
agentfud_password_manager/commands/cmd_info.py
agentfud_password_manager/commands/cmd_init.py
agentfud_password_manager/commands/cmd_list.py
agentfud_password_manager-0.0.4.dist-info/LICENSE
agentfud_password_manager-0.0.4.dist-info/METADATA
agentfud_password_manager-0.0.4.dist-info/WHEEL
agentfud_password_manager-0.0.4.dist-info/entry_points.txt
agentfud_password_manager-0.0.4.dist-info/top_level.txt
agentfud_password_manager-0.0.4.dist-info/RECORD
